{
    "output": {
        "path": null,
        "tmp": "tmp",
        "compress": true
    },
    "structure": {
        "numPointsHint": null,
        "nullDepth": 6,
        "baseDepth": 10,
        "pointsPerChunk": 262144,
        "dynamicChunks": true,
        "type": "hybrid",
        "prefixIds": false
    },
    "geometry": {
        "bbox": null,
        "reproject": null,
        "schema": null
    },
    "input": {
        "run": null,
        "threads": 9,
        "trustHeaders": true,
        "manifest": null
    }
}

